pygdbmi/IoManager.py
pygdbmi/StringStream.py
pygdbmi/__init__.py
pygdbmi/constants.py
pygdbmi/gdbcontroller.py
pygdbmi/gdbmiparser.py
pygdbmi/printcolor.py
pygdbmi/py.typed
pygdbmi-0.10.0.1.dist-info/LICENSE
pygdbmi-0.10.0.1.dist-info/METADATA
pygdbmi-0.10.0.1.dist-info/WHEEL
pygdbmi-0.10.0.1.dist-info/top_level.txt
pygdbmi-0.10.0.1.dist-info/RECORD
