Metadata-Version: 2.1
Name: pygdbmi
Version: 0.10.0.1
Summary: Parse gdb machine interface output with Python
Home-page: https://github.com/cs01/pygdbmi
Author: Chad Smith
Author-email: grassfedcode@gmail.com
License: MIT
Keywords: gdb,python,machine-interface,parse,frontend
Platform: UNKNOWN
Classifier: Intended Audience :: Developers
Classifier: License :: OSI Approved :: MIT License
Classifier: Operating System :: OS Independent
Classifier: Programming Language :: Python
Classifier: Programming Language :: Python :: 3
Classifier: Programming Language :: Python :: 3.6
Classifier: Programming Language :: Python :: 3.7
Classifier: Programming Language :: Python :: 3.8
Classifier: Programming Language :: Python :: Implementation :: PyPy
